Core/DLDCA/Lab/Inlabs/00_inlab/verilog_setup/rtl/common.svh
//==============================================================================
// File    : common.svh
// Project : Simple Processor
//
// Common definitions shared across RTL modules.
//==============================================================================

`ifndef COMMON_SVH
`define COMMON_SVH


// -----------------------------------------------------------------------------
// Global Parameters
// -----------------------------------------------------------------------------

`define XLEN        8
`define REG_COUNT   8
`define REG_ADDR_W  3

// -----------------------------------------------------------------------------
// ALU Operations
// -----------------------------------------------------------------------------

typedef enum logic [2:0] {
    OP_ADD  = 3'd0,
    OP_SUB  = 3'd1,
    OP_AND  = 3'd2,
    OP_OR   = 3'd3,
    OP_XOR  = 3'd4,
    OP_PASS = 3'd5
} alu_op_t;

// -----------------------------------------------------------------------------
// Helper Macros
// -----------------------------------------------------------------------------

`define ZERO {`XLEN{1'b0}}

`ifdef DEBUG
    `define DBG(msg) $display("[DEBUG] %s", msg)
`else
    `define DBG(msg)
`endif

`default_nettype wire

`endif // COMMON_SVH

Core/DLDCA/Lab/Inlabs/00_inlab/verilog_setup/rtl/alu.sv
//==============================================================================
// File    : alu.sv
// Project : Simple Processor
//
// 8-bit Arithmetic Logic Unit
//==============================================================================

`timescale 1ns / 1ps
`default_nettype none

`include "common.svh"

module alu #(
    parameter int XLEN = `XLEN
)(
    input  logic [XLEN-1:0] lhs_i,
    input  logic [XLEN-1:0] rhs_i,
    input  alu_op_t         op_i,

    output logic [XLEN-1:0] result_o,
    output logic            zero_o
);

    //--------------------------------------------------------------------------
    // Combinational ALU
    //--------------------------------------------------------------------------

    always_comb begin
        result_o = `ZERO;

        case (op_i)
            OP_ADD : result_o = lhs_i + rhs_i;
            OP_SUB : result_o = lhs_i - rhs_i;
            OP_AND : result_o = lhs_i & rhs_i;
            OP_OR  : result_o = lhs_i | rhs_i;
            OP_XOR : result_o = lhs_i ^ rhs_i;
            OP_PASS: result_o = lhs_i;

            default: result_o = `ZERO;
        endcase
    end

    //--------------------------------------------------------------------------
    // Status Flags
    //--------------------------------------------------------------------------

    assign zero_o = (result_o == `ZERO);

`ifdef DEBUG
always @(lhs_i, rhs_i, op_i) begin
    $display("[%0t] ALU lhs=%0d rhs=%0d op=%0d result=%0d",
             $time, lhs_i, rhs_i, op_i, result_o);
end
`endif

endmodule

`default_nettype wire

Core/DLDCA/Lab/Inlabs/00_inlab/verilog_setup/rtl/regfile.sv
//==============================================================================
// File    : regfile.sv
// Project : Simple Processor
//
// 8 × 8-bit Register File
// - Two asynchronous read ports
// - One synchronous write port
//==============================================================================

`timescale 1ns / 1ps
`default_nettype none

`include "common.svh"

module regfile #(
    parameter int XLEN      = `XLEN,
    parameter int REG_COUNT = `REG_COUNT,
    parameter int ADDR_W    = `REG_ADDR_W
)(
    input  logic              clk_i,
    input  logic              rst_i,

    input  logic              we_i,
    input  logic [ADDR_W-1:0] rd_addr_i,
    input  logic [XLEN-1:0]   rd_data_i,

    input  logic [ADDR_W-1:0] rs1_addr_i,
    input  logic [ADDR_W-1:0] rs2_addr_i,

    output logic [XLEN-1:0]   rs1_data_o,
    output logic [XLEN-1:0]   rs2_data_o
);

    //--------------------------------------------------------------------------
    // Register Storage
    //--------------------------------------------------------------------------

    logic [XLEN-1:0] regs [0:REG_COUNT-1];

    //--------------------------------------------------------------------------
    // Synchronous Reset / Write
    //--------------------------------------------------------------------------

    always_ff @(posedge clk_i) begin
        if (rst_i) begin
            for (int i = 0; i < REG_COUNT; i++)
                regs[i] <= '0;
        end
        else if (we_i) begin
            regs[rd_addr_i] <= rd_data_i;
        end
    end

    //--------------------------------------------------------------------------
    // Asynchronous Read Ports
    //--------------------------------------------------------------------------

    assign rs1_data_o = regs[rs1_addr_i];
    assign rs2_data_o = regs[rs2_addr_i];

`ifdef DEBUG
    always @(posedge clk_i) begin
        if (we_i && !rst_i) begin
            $strobe("[%0t] RF: R%0d <= 0x%02h",
                     $time, rd_addr_i, rd_data_i);
        end
    end
`endif

endmodule

Core/DLDCA/Lab/Inlabs/00_inlab/verilog_setup/rtl/top.sv
//==============================================================================
// File    : top.sv
// Project : Simple Processor
//
// Datapath:
//   Register File --> ALU --> Register File
//
// One ALU operation is executed whenever write_enable is asserted.
//==============================================================================

`timescale 1ns / 1ps
`default_nettype none

`include "common.svh"

module top #(
    parameter int XLEN   = `XLEN,
    parameter int ADDR_W = `REG_ADDR_W
)(
    input  logic              clk_i,
    input  logic              rst_i,

    input  logic [ADDR_W-1:0] rs1_addr_i,
    input  logic [ADDR_W-1:0] rs2_addr_i,
    input  logic [ADDR_W-1:0] rd_addr_i,

    input  alu_op_t           alu_op_i,

    input  logic              write_enable_i,

    input  logic              external_write_i,
    input  logic [XLEN-1:0]   external_data_i,

    output logic [XLEN-1:0]   rs1_data_o,
    output logic [XLEN-1:0]   rs2_data_o,
    output logic [XLEN-1:0]   result_o,
    output logic              zero_o
);

    //-------------------------------------------------------------------------
    // Internal Signals
    //-------------------------------------------------------------------------

    logic [XLEN-1:0] alu_result;
    logic [XLEN-1:0] write_data;

    //-------------------------------------------------------------------------
    // Register File
    //-------------------------------------------------------------------------

    assign write_data = external_write_i ? external_data_i : alu_result;

    regfile #(
        .XLEN(XLEN)
    ) u_regfile (
        .clk_i      (clk_i),
        .rst_i      (rst_i),

        .we_i       (write_enable_i),
        .rd_addr_i  (rd_addr_i),
        .rd_data_i  (write_data),

        .rs1_addr_i (rs1_addr_i),
        .rs2_addr_i (rs2_addr_i),

        .rs1_data_o (rs1_data_o),
        .rs2_data_o (rs2_data_o)
    );

    //-------------------------------------------------------------------------
    // ALU
    //-------------------------------------------------------------------------

    alu #(
        .XLEN(XLEN)
    ) u_alu (
        .lhs_i    (rs1_data_o),
        .rhs_i    (rs2_data_o),
        .op_i     (alu_op_i),

        .result_o (alu_result),
        .zero_o   (zero_o)
    );

    //-------------------------------------------------------------------------
    // Outputs
    //-------------------------------------------------------------------------

    assign result_o = alu_result;

`ifdef DEBUG
    always @(posedge clk_i) begin
        if (write_enable_i) begin
            $strobe(
                "[%0t] R%0d(%0d) OP=%0d R%0d(%0d) -> R%0d = %0d",
                $time,
                rs1_addr_i, rs1_data_o,
                alu_op_i,
                rs2_addr_i, rs2_data_o,
                rd_addr_i, alu_result
            );
        end
    end
`endif

endmodule

Core/DLDCA/Lab/Inlabs/00_inlab/verilog_setup/tb/tb_top.sv
//==============================================================================
// File    : tb_top.sv
// Project : Tiny Processing Unit (TPU)
// Description:
//   Simple testbench demonstrating clock generation, reset,
//   register initialization, ALU operations and VCD dumping.
//
//==============================================================================

`timescale 1ns/1ps
`include "../rtl/common.svh"

module tb_top;

    //--------------------------------------------------------------------------
    // Clock / Reset
    //--------------------------------------------------------------------------

    logic clk;
    logic rst;

    //--------------------------------------------------------------------------
    // DUT Inputs
    //--------------------------------------------------------------------------

    logic [`REG_ADDR_W-1:0] rs1_addr;
    logic [`REG_ADDR_W-1:0] rs2_addr;
    logic [`REG_ADDR_W-1:0] rd_addr;

    logic                   write_enable;
    alu_op_t                alu_op;

    logic external_write;
    logic [`XLEN-1:0] external_data;

    //--------------------------------------------------------------------------
    // DUT Outputs
    //--------------------------------------------------------------------------

    logic [`XLEN-1:0] rs1_data;
    logic [`XLEN-1:0] rs2_data;
    logic [`XLEN-1:0] result;
    logic             zero;

    //--------------------------------------------------------------------------
    // DUT
    //--------------------------------------------------------------------------

    top dut (
        .clk_i          (clk),
        .rst_i          (rst),

        .rs1_addr_i     (rs1_addr),
        .rs2_addr_i     (rs2_addr),
        .rd_addr_i      (rd_addr),

        .alu_op_i       (alu_op),
        .write_enable_i (write_enable),

        .external_write_i (external_write),
        .external_data_i  (external_data),

        .rs1_data_o     (rs1_data),
        .rs2_data_o     (rs2_data),
        .result_o       (result),
        .zero_o         (zero)
    );

    //--------------------------------------------------------------------------
    // Clock Generator
    //--------------------------------------------------------------------------

    initial clk = 0;
    always #5 clk = ~clk;

    //--------------------------------------------------------------------------
    // Waveform Dump
    //--------------------------------------------------------------------------

    `ifndef DUMPFILE
    `define DUMPFILE "tb_top_dump.vcd"
    `endif

    initial begin
        $dumpfile(`DUMPFILE);
        $dumpvars(0, tb_top);
    end

    initial begin
        external_write = 1'b0;
        external_data  = '0;
    end

    //--------------------------------------------------------------------------
    // Helper Tasks
    //--------------------------------------------------------------------------

    // Directly initialize register file (simulation only)
    task automatic load_reg(
        input logic [`REG_ADDR_W-1:0] addr,
        input logic [`XLEN-1:0] value
    );
    begin
        @(negedge clk);
        rd_addr        <= addr;
        external_data  <= value;
        external_write <= 1'b1;
        write_enable   <= 1'b1;

        @(posedge clk);
        external_write <= 1'b0;
        write_enable   <= 1'b0;
    end
    endtask

    task automatic execute(
        input logic [`REG_ADDR_W-1:0] rs1,
        input logic [`REG_ADDR_W-1:0] rs2,
        input logic [`REG_ADDR_W-1:0] rd,
        input alu_op_t                op
    );
    begin
        @(negedge clk);
        rs1_addr     <= rs1;
        rs2_addr     <= rs2;
        rd_addr      <= rd;
        alu_op       <= op;
        write_enable <= 1'b1;

        @(posedge clk);
        // Standard $display evaluates immediately while automatic task variables are valid
        $display("[%0t] OP=%0d  R%0d(%0d)  R%0d(%0d) -> R%0d = %0d",
                $time, op, rs1, rs1_data, rs2, rs2_data, rd, result);

        write_enable <= 1'b0;
    end
    endtask

    //--------------------------------------------------------------------------
    // Monitor
    //--------------------------------------------------------------------------

    // initial begin
    //     $monitor("[%0t] rst=%0b we=%0b op=%0d result=%0d zero=%0b",
    //               $time, rst, write_enable, alu_op, result, zero);
    // end

    //--------------------------------------------------------------------------
    // Test Sequence
    //--------------------------------------------------------------------------

    initial begin

        // Defaults
        rst           = 1'b1;
        write_enable  = 1'b0;

        rs1_addr      = '0;
        rs2_addr      = '0;
        rd_addr       = '0;

        alu_op        = OP_ADD;

        // Hold reset
        repeat (2) @(posedge clk);
        rst = 1'b0;

        // -------------------------------------------------------------
        // Preload Registers
        // -------------------------------------------------------------

        load_reg(0, 8'd10);
        load_reg(1, 8'd20);
        load_reg(2, 8'd5);
        load_reg(3, 8'd3);

        // -------------------------------------------------------------
        // Example Operations
        // -------------------------------------------------------------

        execute(0, 1, 4, OP_ADD);   // R4 = 30
        execute(1, 2, 5, OP_SUB);   // R5 = 15
        execute(0, 3, 6, OP_AND);
        execute(0, 3, 7, OP_OR);
        execute(4, 5, 0, OP_XOR);
        execute(7, 7, 1, OP_PASS);

        // -------------------------------------------------------------
        // Show Final Register File
        // -------------------------------------------------------------

        $display("\nFinal Register File:");

        for (int i = 0; i < `REG_COUNT; i++) begin
            $display("R%0d = %0d", i, dut.u_regfile.regs[i]);
        end

        $display("\nSimulation Complete.");

        #20;
        $finish;
    end

endmodule

Core/DLDCA/Lab/Inlabs/00_inlab/verilog_setup/build/dump.vcd
$date
	Sat Aug  1 23:14:14 2026
$end
$version
	Icarus Verilog
$end
$timescale
	1ps
$end
$scope module tb_top $end
$var wire 1 ! zero $end
$var wire 8 " rs2_data [7:0] $end
$var wire 8 # rs1_data [7:0] $end
$var wire 8 $ result [7:0] $end
$var reg 3 % alu_op [2:0] $end
$var reg 1 & clk $end
$var reg 8 ' external_data [7:0] $end
$var reg 1 ( external_write $end
$var reg 3 ) rd_addr [2:0] $end
$var reg 3 * rs1_addr [2:0] $end
$var reg 3 + rs2_addr [2:0] $end
$var reg 1 , rst $end
$var reg 1 - write_enable $end
$scope module dut $end
$var wire 3 . alu_op_i [2:0] $end
$var wire 1 & clk_i $end
$var wire 8 / external_data_i [7:0] $end
$var wire 1 ( external_write_i $end
$var wire 3 0 rd_addr_i [2:0] $end
$var wire 8 1 result_o [7:0] $end
$var wire 3 2 rs1_addr_i [2:0] $end
$var wire 3 3 rs2_addr_i [2:0] $end
$var wire 1 , rst_i $end
$var wire 1 - write_enable_i $end
$var wire 1 ! zero_o $end
$var wire 8 4 write_data [7:0] $end
$var wire 8 5 rs2_data_o [7:0] $end
$var wire 8 6 rs1_data_o [7:0] $end
$var wire 8 7 alu_result [7:0] $end
$var parameter 32 8 ADDR_W $end
$var parameter 32 9 XLEN $end
$scope module u_alu $end
$var wire 3 : op_i [2:0] $end
$var wire 1 ! zero_o $end
$var wire 8 ; rhs_i [7:0] $end
$var wire 8 < lhs_i [7:0] $end
$var parameter 32 = XLEN $end
$var reg 8 > result_o [7:0] $end
$upscope $end
$scope module u_regfile $end
$var wire 1 & clk_i $end
$var wire 3 ? rd_addr_i [2:0] $end
$var wire 8 @ rd_data_i [7:0] $end
$var wire 3 A rs1_addr_i [2:0] $end
$var wire 8 B rs1_data_o [7:0] $end
$var wire 3 C rs2_addr_i [2:0] $end
$var wire 8 D rs2_data_o [7:0] $end
$var wire 1 , rst_i $end
$var wire 1 - we_i $end
$var parameter 32 E ADDR_W $end
$var parameter 32 F REG_COUNT $end
$var parameter 32 G XLEN $end
$scope begin $ivl_for_loop0 $end
$var integer 32 H i [31:0] $end
$upscope $end
$upscope $end
$upscope $end
$scope begin $ivl_for_loop1 $end
$var integer 32 I i [31:0] $end
$upscope $end
$scope task execute $end
$upscope $end
$scope task load_reg $end
$upscope $end
$upscope $end
$enddefinitions $end
$comment Show the parameter values. $end
$dumpall
b1000 G
b1000 F
b11 E
b1000 =
b1000 9
b11 8
$end
#0
$dumpvars
b0 I
b0 H
bx D
b0 C
bx B
b0 A
bx @
b0 ?
bx >
bx <
bx ;
b0 :
bx 7
bx 6
bx 5
bx 4
b0 3
b0 2
bx 1
b0 0
b0 /
b0 .
0-
1,
b0 +
b0 *
b0 )
0(
b0 '
0&
b0 %
bx $
bx #
bx "
x!
$end
#5000
b0 4
b0 @
1!
b0 $
b0 1
b0 7
b0 >
b0 #
b0 6
b0 <
b0 B
b0 "
b0 5
b0 ;
b0 D
b1000 H
1&
#10000
0&
#15000
b1000 H
0,
1&
#20000
b1010 4
b1010 @
1-
1(
b1010 '
b1010 /
0&
#25000
0!
b10100 $
b10100 1
b10100 7
b10100 >
b10100 4
b10100 @
b1010 #
b1010 6
b1010 <
b1010 B
b1010 "
b1010 5
b1010 ;
b1010 D
0-
0(
1&
#30000
1-
1(
b10100 '
b10100 /
b1 )
b1 0
b1 ?
0&
#35000
0-
0(
1&
#40000
b101 4
b101 @
1-
1(
b101 '
b101 /
b10 )
b10 0
b10 ?
0&
#45000
b10100 4
b10100 @
0-
0(
1&
#50000
b11 4
b11 @
1-
1(
b11 '
b11 /
b11 )
b11 0
b11 ?
0&
#55000
b10100 4
b10100 @
0-
0(
1&
#60000
b11110 4
b11110 @
0!
b11110 $
b11110 1
b11110 7
b11110 >
1-
b100 )
b100 0
b100 ?
b10100 "
b10100 5
b10100 ;
b10100 D
b1 +
b1 3
b1 C
0&
#65000
0-
1&
#70000
b1111 4
b1111 @
0!
b1111 $
b1111 1
b1111 7
b1111 >
1-
b1 %
b1 .
b1 :
b101 )
b101 0
b101 ?
b101 "
b101 5
b101 ;
b101 D
b10 +
b10 3
b10 C
b10100 #
b10100 6
b10100 <
b10100 B
b1 *
b1 2
b1 A
0&
#75000
0-
1&
#80000
b10 4
b10 @
0!
b10 $
b10 1
b10 7
b10 >
1-
b10 %
b10 .
b10 :
b110 )
b110 0
b110 ?
b11 "
b11 5
b11 ;
b11 D
b11 +
b11 3
b11 C
b1010 #
b1010 6
b1010 <
b1010 B
b0 *
b0 2
b0 A
0&
#85000
0-
1&
#90000
b1011 4
b1011 @
0!
b1011 $
b1011 1
b1011 7
b1011 >
1-
b11 %
b11 .
b11 :
b111 )
b111 0
b111 ?
0&
#95000
0-
1&
#100000
b10001 4
b10001 @
0!
b10001 $
b10001 1
b10001 7
b10001 >
1-
b100 %
b100 .
b100 :
b0 )
b0 0
b0 ?
b1111 "
b1111 5
b1111 ;
b1111 D
b101 +
b101 3
b101 C
b11110 #
b11110 6
b11110 <
b11110 B
b100 *
b100 2
b100 A
0&
#105000
0-
1&
#110000
b1011 4
b1011 @
0!
b1011 $
b1011 1
b1011 7
b1011 >
1-
b101 %
b101 .
b101 :
b1 )
b1 0
b1 ?
b1011 "
b1011 5
b1011 ;
b1011 D
b111 +
b111 3
b111 C
b1011 #
b1011 6
b1011 <
b1011 B
b111 *
b111 2
b111 A
0&
#115000
0-
b1000 I
1&
